multimodaltranslation/__init__.py
multimodaltranslation/__main__.py
multimodaltranslation/audio/__init__.py
multimodaltranslation/audio/install_models.py
multimodaltranslation/audio/translate.py
multimodaltranslation/main.py
multimodaltranslation/readme.rst
multimodaltranslation/server.py
multimodaltranslation/text/__init__.py
multimodaltranslation/text/translate.py
multimodaltranslation/version.py
multimodaltranslation/video/__init__.py
multimodaltranslation/video/translate.py
multimodal_translation-1.0.1.dist-info/METADATA
multimodal_translation-1.0.1.dist-info/WHEEL
multimodal_translation-1.0.1.dist-info/entry_points.txt
multimodal_translation-1.0.1.dist-info/licenses/AUTHORS.md
multimodal_translation-1.0.1.dist-info/licenses/LICENSE
multimodal_translation-1.0.1.dist-info/RECORD
