Metadata-Version: 2.4
Name: multimodal-translation
Version: 1.0.1
Summary: AI based translation from one language to many 
License-Expression: AGPL-3.0-only
License-File: AUTHORS.md
License-File: LICENSE
Keywords: Multimodal Translator,AI Translation
Author: Iso
Author-email: iso.techdev@gmail.com
Maintainer: Iso
Requires-Python: >=3.9,<4.0
Classifier: Development Status :: 5 - Production/Stable
Classifier: Intended Audience :: Education
Classifier: Intended Audience :: Other Audience
Classifier: License :: OSI Approved :: GNU Affero General Public License v3
Classifier: Natural Language :: English
Classifier: Operating System :: Unix
Classifier: Operating System :: POSIX :: Linux
Classifier: Operating System :: MacOS
Classifier: Programming Language :: Python :: 3 :: Only
Classifier: Programming Language :: Python :: 3.8
Classifier: Programming Language :: Python :: 3.9
Classifier: Programming Language :: Python :: 3.10
Classifier: Programming Language :: Python :: 3.11
Classifier: Programming Language :: Python :: 3.12
Classifier: Programming Language :: Python :: 3.13
Classifier: Topic :: Multimedia
Provides-Extra: docs
Provides-Extra: test
Requires-Dist: Sphinx (<=8.2.3) ; (python_version >= "3.11" and python_version <= "3.14") and (extra == "docs")
Requires-Dist: appdirs (==1.4.4)
Requires-Dist: argostranslate (==1.10.0)
Requires-Dist: coveralls ; extra == "test"
Requires-Dist: pocketsphinx (==5.0.4)
Requires-Dist: pytest (>=8.4.0) ; (python_version >= "3.9" and python_version <= "3.14") and (extra == "test")
Requires-Dist: pytest-cov (>=6) ; (python_version >= "3.9" and python_version <= "3.13") and (extra == "test")
Requires-Dist: pytest-mock (>=3.14.0) ; (python_version >= "3.9" and python_version <= "3.14") and (extra == "test")
Requires-Dist: sphinx-autobuild (==2024.10.3) ; (python_version >= "3.9" and python_version <= "3.14") and (extra == "docs")
Requires-Dist: sphinx-autodoc-typehints (<=3.2.0) ; (python_version >= "3.11" and python_version <= "3.14") and (extra == "docs")
Requires-Dist: sphinx-inline-tabs (==2023.4.21) ; (python_version >= "3.8" and python_version <= "3.14") and (extra == "docs")
Requires-Dist: sphinx-rtd-theme (<=3.0.2) ; (python_version >= "3.8" and python_version <= "3.14") and (extra == "docs")
Requires-Dist: sphinxcontrib-mermaid (<=1.0.0) ; (python_version >= "3.8" and python_version <= "3.14") and (extra == "docs")
Requires-Dist: sphinxcontrib-spelling (<=8.0.1) ; (python_version >= "3.10" and python_version <= "3.14") and (extra == "docs")
Requires-Dist: vosk (>=0.3.45)
Project-URL: Bug Tracker, https://github.com/Issamricin/multimodal-translation/issues
Project-URL: CI: Github Actions, https://github.com/Issamricin/multimodal-translation/actions
Project-URL: Changelog, https://github.com/Issamricin/multimodal-translation/blob/main/CHANGELOG.rst
Project-URL: Documentation, https://multimodal-translation.readthedocs.io/
Project-URL: Source Code, https://github.com/Issamricin/multimodal-translation
